{
  "version": "0.0.1",
  "name": "jito_tip_router",
  "instructions": [
    {
      "name": "InitializeNCNConfig",
      "accounts": [
        {
          "name": "restakingConfig",
          "isMut": false,
          "isSigner": false
        },
        {
          "name": "ncnConfig",
          "isMut": true,
          "isSigner": false
        },
        {
          "name": "ncn",
          "isMut": false,
          "isSigner": false
        },
        {
          "name": "ncnAdmin",
          "isMut": false,
          "isSigner": true
        },
        {
          "name": "feeWallet",
          "isMut": false,
          "isSigner": false
        },
        {
          "name": "tieBreakerAdmin",
          "isMut": false,
          "isSigner": false
        },
        {
          "name": "restakingProgramId",
          "isMut": false,
          "isSigner": false
        },
        {
          "name": "systemProgram",
          "isMut": false,
          "isSigner": false
        }
      ],
      "args": [
        {
          "name": "daoFeeBps",
          "type": "u64"
        },
        {
          "name": "ncnFeeBps",
          "type": "u64"
        },
        {
          "name": "blockEngineFeeBps",
          "type": "u64"
        }
      ],
      "discriminant": {
        "type": "u8",
        "value": 0
      }
    },
    {
      "name": "SetConfigFees",
      "accounts": [
        {
          "name": "restakingConfig",
          "isMut": false,
          "isSigner": false
        },
        {
          "name": "config",
          "isMut": true,
          "isSigner": false
        },
        {
          "name": "ncn",
          "isMut": false,
          "isSigner": false
        },
        {
          "name": "ncnAdmin",
          "isMut": false,
          "isSigner": true
        },
        {
          "name": "restakingProgramId",
          "isMut": false,
          "isSigner": false
        }
      ],
      "args": [
        {
          "name": "newDaoFeeBps",
          "type": {
            "option": "u64"
          }
        },
        {
          "name": "newNcnFeeBps",
          "type": {
            "option": "u64"
          }
        },
        {
          "name": "newBlockEngineFeeBps",
          "type": {
            "option": "u64"
          }
        },
        {
          "name": "newFeeWallet",
          "type": {
            "option": "publicKey"
          }
        }
      ],
      "discriminant": {
        "type": "u8",
        "value": 1
      }
    },
    {
      "name": "SetNewAdmin",
      "accounts": [
        {
          "name": "config",
          "isMut": true,
          "isSigner": false
        },
        {
          "name": "ncn",
          "isMut": false,
          "isSigner": false
        },
        {
          "name": "ncnAdmin",
          "isMut": false,
          "isSigner": true
        },
        {
          "name": "newAdmin",
          "isMut": false,
          "isSigner": false
        },
        {
          "name": "restakingProgramId",
          "isMut": false,
          "isSigner": false
        }
      ],
      "args": [
        {
          "name": "role",
          "type": {
            "defined": "ConfigAdminRole"
          }
        }
      ],
      "discriminant": {
        "type": "u8",
        "value": 2
      }
    },
    {
      "name": "InitializeWeightTable",
      "accounts": [
        {
          "name": "restakingConfig",
          "isMut": false,
          "isSigner": false
        },
        {
          "name": "ncnConfig",
          "isMut": false,
          "isSigner": false
        },
        {
          "name": "ncn",
          "isMut": false,
          "isSigner": false
        },
        {
          "name": "weightTable",
          "isMut": true,
          "isSigner": false
        },
        {
          "name": "payer",
          "isMut": true,
          "isSigner": true
        },
        {
          "name": "restakingProgramId",
          "isMut": false,
          "isSigner": false
        },
        {
          "name": "systemProgram",
          "isMut": false,
          "isSigner": false
        }
      ],
      "args": [
        {
          "name": "firstSlotOfNcnEpoch",
          "type": {
            "option": "u64"
          }
        }
      ],
      "discriminant": {
        "type": "u8",
        "value": 3
      }
    },
    {
      "name": "AdminUpdateWeightTable",
      "accounts": [
        {
          "name": "ncn",
          "isMut": false,
          "isSigner": false
        },
        {
          "name": "weightTable",
          "isMut": true,
          "isSigner": false
        },
        {
          "name": "weightTableAdmin",
          "isMut": false,
          "isSigner": true
        },
        {
          "name": "mint",
          "isMut": false,
          "isSigner": false
        },
        {
          "name": "restakingProgramId",
          "isMut": false,
          "isSigner": false
        }
      ],
      "args": [
        {
          "name": "ncnEpoch",
          "type": "u64"
        },
        {
          "name": "weight",
          "type": "u128"
        }
      ],
      "discriminant": {
        "type": "u8",
        "value": 4
      }
    },
    {
      "name": "RegisterMint",
      "accounts": [
        {
          "name": "restakingConfig",
          "isMut": false,
          "isSigner": false
        },
        {
          "name": "trackedMints",
          "isMut": true,
          "isSigner": false
        },
        {
          "name": "ncn",
          "isMut": false,
          "isSigner": false
        },
        {
          "name": "vault",
          "isMut": false,
          "isSigner": false
        },
        {
          "name": "vaultNcnTicket",
          "isMut": false,
          "isSigner": false
        },
        {
          "name": "ncnVaultTicket",
          "isMut": false,
          "isSigner": false
        },
        {
          "name": "restakingProgramId",
          "isMut": false,
          "isSigner": false
        },
        {
          "name": "vaultProgramId",
          "isMut": false,
          "isSigner": false
        }
      ],
      "args": [],
      "discriminant": {
        "type": "u8",
        "value": 5
      }
    },
    {
      "name": "InitializeTrackedMints",
      "accounts": [
        {
          "name": "ncnConfig",
          "isMut": false,
          "isSigner": false
        },
        {
          "name": "trackedMints",
          "isMut": true,
          "isSigner": false
        },
        {
          "name": "ncn",
          "isMut": false,
          "isSigner": false
        },
        {
          "name": "payer",
          "isMut": true,
          "isSigner": true
        },
        {
          "name": "systemProgram",
          "isMut": false,
          "isSigner": false
        }
      ],
      "args": [],
      "discriminant": {
        "type": "u8",
        "value": 6
      }
    }
  ],
  "accounts": [
    {
      "name": "NcnConfig",
      "type": {
        "kind": "struct",
        "fields": [
          {
            "name": "ncn",
            "type": "publicKey"
          },
          {
            "name": "tieBreakerAdmin",
            "type": "publicKey"
          },
          {
            "name": "feeAdmin",
            "type": "publicKey"
          },
          {
            "name": "fees",
            "type": {
              "defined": "Fees"
            }
          },
          {
            "name": "bump",
            "type": "u8"
          },
          {
            "name": "reserved",
            "type": {
              "array": [
                "u8",
                127
              ]
            }
          }
        ]
      }
    },
    {
      "name": "TrackedMints",
      "type": {
        "kind": "struct",
        "fields": [
          {
            "name": "ncn",
            "type": "publicKey"
          },
          {
            "name": "bump",
            "type": "u8"
          },
          {
            "name": "reserved",
            "type": {
              "array": [
                "u8",
                7
              ]
            }
          },
          {
            "name": "stMintList",
            "type": {
              "array": [
                {
                  "defined": "MintEntry"
                },
                2
              ]
            }
          }
        ]
      }
    },
    {
      "name": "WeightTable",
      "type": {
        "kind": "struct",
        "fields": [
          {
            "name": "ncn",
            "type": "publicKey"
          },
          {
            "name": "ncnEpoch",
            "type": {
              "defined": "PodU64"
            }
          },
          {
            "name": "slotCreated",
            "type": {
              "defined": "PodU64"
            }
          },
          {
            "name": "bump",
            "type": "u8"
          },
          {
            "name": "reserved",
            "type": {
              "array": [
                "u8",
                128
              ]
            }
          },
          {
            "name": "table",
            "type": {
              "array": [
                {
                  "defined": "WeightEntry"
                },
                32
              ]
            }
          }
        ]
      }
    }
  ],
  "types": [
    {
      "name": "Fees",
      "type": {
        "kind": "struct",
        "fields": [
          {
            "name": "fee1",
            "type": {
              "defined": "Fee"
            }
          },
          {
            "name": "fee2",
            "type": {
              "defined": "Fee"
            }
          }
        ]
      }
    },
    {
      "name": "Fee",
      "type": {
        "kind": "struct",
        "fields": [
          {
            "name": "wallet",
            "type": "publicKey"
          },
          {
            "name": "daoShareBps",
            "type": {
              "defined": "PodU64"
            }
          },
          {
            "name": "ncnShareBps",
            "type": {
              "defined": "PodU64"
            }
          },
          {
            "name": "blockEngineFeeBps",
            "type": {
              "defined": "PodU64"
            }
          },
          {
            "name": "activationEpoch",
            "type": {
              "defined": "PodU64"
            }
          }
        ]
      }
    },
    {
      "name": "MintEntry",
      "type": {
        "kind": "struct",
        "fields": [
          {
            "name": "stMint",
            "type": "publicKey"
          },
          {
            "name": "vaultIndex",
            "type": {
              "defined": "PodU64"
            }
          }
        ]
      }
    },
    {
      "name": "WeightEntry",
      "type": {
        "kind": "struct",
        "fields": [
          {
            "name": "mint",
            "type": "publicKey"
          },
          {
            "name": "weight",
            "type": {
              "defined": "PodU128"
            }
          },
          {
            "name": "slotSet",
            "type": {
              "defined": "PodU64"
            }
          },
          {
            "name": "slotUpdated",
            "type": {
              "defined": "PodU64"
            }
          },
          {
            "name": "reserved",
            "type": {
              "array": [
                "u8",
                128
              ]
            }
          }
        ]
      }
    },
    {
      "name": "ConfigAdminRole",
      "type": {
        "kind": "enum",
        "variants": [
          {
            "name": "FeeAdmin"
          },
          {
            "name": "TieBreakerAdmin"
          }
        ]
      }
    }
  ],
  "errors": [
    {
      "code": 8448,
      "name": "DenominatorIsZero",
      "msg": "Zero in the denominator"
    },
    {
      "code": 8449,
      "name": "ArithmeticOverflow",
      "msg": "Overflow"
    },
    {
      "code": 8450,
      "name": "ModuloOverflow",
      "msg": "Modulo Overflow"
    },
    {
      "code": 8451,
      "name": "NewPreciseNumberError",
      "msg": "New precise number error"
    },
    {
      "code": 8452,
      "name": "CastToImpreciseNumberError",
      "msg": "Cast to imprecise number error"
    },
    {
      "code": 8704,
      "name": "IncorrectWeightTableAdmin",
      "msg": "Incorrect weight table admin"
    },
    {
      "code": 8705,
      "name": "DuplicateMintsInTable",
      "msg": "Duplicate mints in table"
    },
    {
      "code": 8706,
      "name": "NoMintsInTable",
      "msg": "There are no mints in the table"
    },
    {
      "code": 8707,
      "name": "TooManyMintsForTable",
      "msg": "Too many mints for table"
    },
    {
      "code": 8708,
      "name": "WeightTableAlreadyInitialized",
      "msg": "Weight table already initialized"
    },
    {
      "code": 8709,
      "name": "CannotCreateFutureWeightTables",
      "msg": "Cannnot create future weight tables"
    },
    {
      "code": 8710,
      "name": "WeightMintsDoNotMatchLength",
      "msg": "Weight mints do not match - length"
    },
    {
      "code": 8711,
      "name": "WeightMintsDoNotMatchMintHash",
      "msg": "Weight mints do not match - mint hash"
    },
    {
      "code": 8712,
      "name": "InvalidMintForWeightTable",
      "msg": "Invalid mint for weight table"
    },
    {
      "code": 8713,
      "name": "ConfigMintsNotUpdated",
      "msg": "Config supported mints do not match NCN Vault Count"
    },
    {
      "code": 8714,
      "name": "ConfigMintListFull",
      "msg": "NCN config vaults are at capacity"
    },
    {
      "code": 8715,
      "name": "TrackedMintListFull",
      "msg": "Tracked mints are at capacity"
    },
    {
      "code": 8716,
      "name": "VaultIndexAlreadyInUse",
      "msg": "Vault index already in use by a different mint"
    },
    {
      "code": 8960,
      "name": "FeeCapExceeded",
      "msg": "Fee cap exceeded"
    },
    {
      "code": 9216,
      "name": "IncorrectNcnAdmin",
      "msg": "Incorrect NCN Admin"
    },
    {
      "code": 9217,
      "name": "IncorrectNcn",
      "msg": "Incorrect NCN"
    },
    {
      "code": 9218,
      "name": "IncorrectFeeAdmin",
      "msg": "Incorrect fee admin"
    }
  ],
  "metadata": {
    "origin": "shank",
    "address": "Fv9aHCgvPQSr4jg9W8eTS6Ys1SNmh2qjyATrbsjEMaSH"
  }
}